<xml version="0.995" board="Arduino/Genuino Micro" xmlns="http://www.w3.org/1999/xhtml"><block type="base_setup" id="R2Vo*x`#n|9pC_L:.Pi{" x="-844" y="-373"><statement name="DO"><block type="controls_attachInterrupt" id=".r%qVV*DZojkqGLnoAwp"><field name="mode">RISING</field><value name="PIN"><shadow xmlns="" type="pins_interrupt"><field xmlns="" name="PIN">2</field></shadow><block type="pins_interrupt" id="j*R;iFY!AH?98#~,Q-*."><field name="PIN">2</field></block></value><statement name="DO"><block type="inout_digital_write2" id="EX`@}cTx3m5b){W5m{LK"><value name="PIN"><shadow type="pins_digital" id="eneO*I(Fac8~X#sBE0mz"><field name="PIN">10</field></shadow></value><value name="STAT"><shadow type="inout_highlow" id="zCbarP4HUXy/~c^ZlF~]"><field name="BOOL">HIGH</field></shadow><block type="logic_negate" id="EPNP42GCAKQJeu+4U6Ou"><value name="BOOL"><block type="inout_digital_read2" id="vH%?hTi(o)YcMr[;xK8."><value name="PIN"><shadow xmlns="" type="pins_digital"><field xmlns="" name="PIN">0</field></shadow><block type="pins_digital" id="WCFRvQnH=TXnM3Q!;W^6"><field name="PIN">10</field></block></value></block></value></block></value></block></statement></block></statement></block><block type="controls_if" id="%15j@fdySrUcv_g6`4t3" x="-843" y="-218"><value name="IF0"><block type="inout_digital_read2" id="c!:]!?I]C+Di29_pBOdB"><value name="PIN"><shadow xmlns="" type="pins_digital"><field xmlns="" name="PIN">0</field></shadow><block type="pins_digital" id="k/K;s,+Zl)95M5XSxn7P"><field name="PIN">10</field></block></value></block></value><statement name="DO0"><block type="base_delay" id="~XM2X]k#:{},[_Kf;#oC"><field name="UNIT">delay</field><value name="DELAY_TIME"><shadow xmlns="" type="math_number"><field xmlns="" name="NUM">1000</field></shadow><block type="math_number" id=":./_M4/#AtNpJ]VTMCSj"><field name="NUM">3000</field></block></value></block></statement><next><block type="inout_digital_write2" id=",Y/CuhmWQS]xEy4C,JcJ"><value name="PIN"><shadow xmlns="" type="pins_digital"><field xmlns="" name="PIN">0</field></shadow><block type="pins_digital" id="*_UjuG.KMdTnbo{~P~K?"><field name="PIN">10</field></block></value><value name="STAT"><shadow xmlns="" type="inout_highlow"><field xmlns="" name="BOOL">HIGH</field></shadow><block type="inout_highlow" id="D|?Iw=Q:fJx(NG1gg_Re"><field name="BOOL">LOW</field></block></value></block></next></block></xml>