<xml board="Arduino Uno"><block type="Nova_Motor" x="274" y="196"><field name="PIN">M0</field><value name="speed"><block type="math_number"><field name="NUM">80</field></block></value><next><block type="base_delay"><field name="UNIT">delay</field><value name="DELAY_TIME"><shadow type="math_number"><field name="NUM">1000</field></shadow></value><next><block type="Nova_Motor"><field name="PIN">M0</field><value name="speed"><block type="math_number"><field name="NUM">-80</field></block></value><next><block type="base_delay"><field name="UNIT">delay</field><value name="DELAY_TIME"><shadow type="math_number"><field name="NUM">1000</field></shadow></value><next><block type="Nova_Motor"><field name="PIN">M0</field><value name="speed"><block type="math_number"><field name="NUM">0</field></block></value><next><block type="base_delay"><field name="UNIT">delay</field><value name="DELAY_TIME"><shadow type="math_number"><field name="NUM">1000</field></shadow></value></block></next></block></next></block></next></block></next></block></next></block></xml>